torchplus/__init__.py
torchplus/_jit_internal.py
torchplus/device.py
torchplus/functional.py
torchplus/loss_func.py
torchplus/overrides.py
torchplus/setting.py
torchplus/tensor.py
torchplus/tensor_20210302.py
torchplus/tensor_old.py
torchplus/tensorfunc.py
torchplus/torch_namespace.py
torchplus/nn/__init__.py
torchplus/nn/_reduction.py
torchplus/nn/common_types.py
torchplus/nn/functional.py
torchplus/nn/grad.py
torchplus/nn/init.py
torchplus/nn/parameter.py
torchplus/nn/modules/__init__.py
torchplus/nn/modules/_functions.py
torchplus/nn/modules/activation.py
torchplus/nn/modules/adaptive.py
torchplus/nn/modules/batchnorm.py
torchplus/nn/modules/container.py
torchplus/nn/modules/conv.py
torchplus/nn/modules/distance.py
torchplus/nn/modules/dropout.py
torchplus/nn/modules/flatten.py
torchplus/nn/modules/fold.py
torchplus/nn/modules/instancenorm.py
torchplus/nn/modules/linear.py
torchplus/nn/modules/loss.py
torchplus/nn/modules/module.py
torchplus/nn/modules/normalization.py
torchplus/nn/modules/padding.py
torchplus/nn/modules/pixelshuffle.py
torchplus/nn/modules/pooling.py
torchplus/nn/modules/rnn.py
torchplus/nn/modules/sparse.py
torchplus/nn/modules/transformer.py
torchplus/nn/modules/upsampling.py
torchplus/nn/modules/utils.py
torchplus/nn/utils/__init__.py
torchplus/nn/utils/clip_grad.py
torchplus/nn/utils/convert_parameters.py
torchplus/nn/utils/fusion.py
torchplus/nn/utils/memory_format.py
torchplus/nn/utils/prune.py
torchplus/nn/utils/rnn.py
torchplus/nn/utils/spectral_norm.py
torchplus/nn/utils/weight_norm.py
torchplus-0.2.107.dist-info/METADATA
torchplus-0.2.107.dist-info/WHEEL
torchplus-0.2.107.dist-info/top_level.txt
torchplus-0.2.107.dist-info/RECORD
