Metadata-Version: 2.1
Name: torchplus
Version: 0.2.107
Summary: This package is based on pytorch and try to provide a more user-friendly interface for pytorch. 
Home-page: https://github.com/Bertie97/pyctlib/tree/main/torchplus
Author: Yiteng Zhang, Yuncheng Zhou
Author-email: zytfdu@icloud.com
License: MIT Licence
Keywords: pip,pyctlib,torchplus
Platform: any
Requires-Dist: numpy
Requires-Dist: pyctlib
Requires-Dist: torch (>=1.7.0)
Requires-Dist: pynvml
